triematch/__init__.py
triematch/radix.py
triematch/trie.py
triematch/utils.py
triematch-0.0.1rc0.dist-info/METADATA
triematch-0.0.1rc0.dist-info/WHEEL
triematch-0.0.1rc0.dist-info/top_level.txt
triematch-0.0.1rc0.dist-info/RECORD
