Metadata-Version: 2.1
Name: triematch
Version: 0.0.1rc0
Summary: Fast lookup for string patterns using Trie, Radix & Aho-Corasick algorithms
Author: Jafar Khakpour
License: MIT License
Keywords: triematch,trie,prefix tree,tree,radix,aho-corasick,prefix-tree
Classifier: Development Status :: 4 - Beta
Classifier: Intended Audience :: Developers
Classifier: License :: OSI Approved :: MIT License
Classifier: Operating System :: OS Independent
Classifier: Programming Language :: Python :: 3
Classifier: Programming Language :: Python :: 3.9
Classifier: Topic :: Software Development :: Libraries
Classifier: Topic :: Software Development :: Libraries :: Python Modules
Classifier: Topic :: Utilities
Requires-Python: >=3.9
Requires-Dist: sortedcollections
